{"@context": "http://schema.org", "@type": "Recipe", "nutrition": {}, "image": "https://www.seriouseats.com/recipes/images/20110118strainerprimary.jpg", "author": {"@type": "Person", "name": "Lucy Baker"}, "recipeCuisine": "", "keywords": ["alcohol", "cocktails", "drinks", "gin", "watermelon"], "aggregateRating": {"@type": "AggregateRating", "ratingValue": "", "ratingCount": ""}, "name": "Cook the Book: Mississippi Watermelon-Basil Martini", "link": "https://www.seriouseats.com/recipes/2008/06/mississippi-watermelon-basil-martini-mint-julep-recipe.html", "description": "Here's a recipe that's sure to make your dad forget all about that six-pack in the back of the fridge. The <strong>Mississippi Watermelon-Basil Martini</strong> is made with gin and a hint of lime.", "totalTime": "", "recipeYield": "1 drink", "recipeCategory": ["Cook the Book", "Watermelon"], "recipeIngredient": ["1 cup cubed watermelon", "8 basil leaves", "1 1/4 ounces Tanqueray or other gin", "1/2 ounce simple syrup (1 cup water, 1 cup sugar, heated until sugar dissolves, then cooled)", "2 lime wedges"], "recipeInstructions": [{"@context": "http://schema.org", "@type": "HowToStep", "text": "<p>Place all ingredients in a metal cocktail shaker with ice. Shake well. Strain into a martini glass, and garnish with additional lime if desired.</p>"}]}