{"@context": "http://schema.org", "@type": "Recipe", "nutrition": {}, "image": "https://www.seriouseats.com/2018/06/20180521-broken-pan-sauce-vicky-wasik-13.jpg", "author": {"@type": "Person", "name": "J. Kenji L\u00f3pez-Alt"}, "recipeCuisine": "", "keywords": ["entrees", "meats", "steaks", "The Food Lab", "wine"], "aggregateRating": {"@type": "AggregateRating", "ratingValue": "1", "ratingCount": "1"}, "name": "Pan-Seared Steaks with Red Wine Pan Sauce", "link": "https://www.seriouseats.com/recipes/2009/12/pan-seared-steaks-with-red-wine-pan-sauce-recipe.html", "description": "Note: Want to know why it's important to rest your steak? Check it out here....", "totalTime": "", "recipeYield": "4", "recipeCategory": ["Beef", "Condiments and Sauces", "Mains", "The Food Lab"], "recipeIngredient": ["<strong>For the steak:</strong>", "4 steaks, 1 1/2 to 1 3/4 inches thick, about 8-ounces each (see note)", "kosher salt", "freshly ground black pepper", "2 tablespoons vegetable oil", "1 tablespoon butter", "4 sprigs thyme", "1 shallot, sliced thin", "<strong>For the pan sauce (optional):</strong>", "1 shallot, finely minced", "1 cup low-sodium chicken broth", "1 cup dry red wine", "1 tablespoon dijon mustard", "1 tablespoon minced parsley", "2 tablespoons unsalted butter", "1 teaspoon lemon juice", "Salt and pepper to taste"], "recipeInstructions": [{"@context": "http://schema.org", "@type": "HowToStep", "text": "<p>Season steaks generously on all surfaces with kosher salt and black pepper. Add vegetable oil to 12-inch, heavy-bottomed cast iron or stainless steel skillet. Heat over high heat until oil just begins to smoke. Add steaks to pan, and cook without moving until deep golden-brown crust develops on first side, three to four minutes. Flip steaks over.</p>"}, {"@context": "http://schema.org", "@type": "HowToStep", "text": "<p>Add butter, thyme sprigs, and shallots to pan. Turn heat down to medium-high. Continue to cook, occasionally basting steaks by tilting pan towards you and spooning hot fat over surface of steaks. If steaks start to become too dark, turn lower heat. Continue to cook until instant-read thermometer inserted in to center of steak registers 125\u00b0F for medium-rare (between three and seven minutes, depending on how powerful your range is). Remove steaks from pan, place on rack set in rimmed baking sheet, pour fat, shallots, and thyme from pan over steaks, tent loosely with aluminum foil, and allow to rest for until center of steak cools to 120\u00b0F (about ten minutes). Meanwhile, make pan sauce if desired.</p>"}]}