{"@context": "http://schema.org", "@type": "Recipe", "nutrition": {}, "image": "https://www.seriouseats.com/recipes/images/20100129-anejohighball-recipe.jpg", "author": {"@type": "Person", "name": "Paul Clarke"}, "recipeCuisine": "", "keywords": ["cocktails", "rum", "Time for a Drink"], "aggregateRating": {"@type": "AggregateRating", "ratingValue": "", "ratingCount": ""}, "name": "Anejo Highball", "link": "https://www.seriouseats.com/recipes/2010/01/anejo-highball-drinks-recipe-rum-ginger-beer.html", "description": "Anejo Highball. [Flickr: teamperks] During the dark, dry years of Prohibition, thousands of thirsty Americans made it a point of vacationing in Cuba. Not only did the island nation offer an alluring Caribbean climate, but Havana was home to...", "totalTime": "", "recipeYield": "", "recipeCategory": ["Ginger", "Rum"], "recipeIngredient": ["1 1/2 ounces aged rum", "1/2 ounce orange curacao (or Grand Marnier)", "1/4 ounce fresh lime juice", "2 ounces chilled <a href=\"http://www.seriouseats.com/2009/07/ginger-beer-taste-test-gus-ginger-people-reeds-fentimans-great-uncle-cornelius.html\">ginger beer</a>", "2 dashes Angostura bitters"], "recipeInstructions": [{"@context": "http://schema.org", "@type": "HowToStep", "text": "<p>Combine rum, curacao, lime juice and bitters in a highball glass. Stir to combine and fill glass with ice; top with ginger beer. Garnish with a lime wheel and an orange slice.</p>"}]}