{"@context": "http://schema.org", "@type": "Recipe", "nutrition": {}, "image": "https://www.seriouseats.com/recipes/images/2011/10/20111007-PDT-ApplejackRabbit.jpg", "author": {"@type": "Person", "name": "The Serious Eats Team"}, "recipeCuisine": "", "keywords": ["apple brandy", "cocktail", "fall", "orange juice"], "aggregateRating": {"@type": "AggregateRating", "ratingValue": "", "ratingCount": ""}, "name": "Applejack Rabbit", "link": "https://www.seriouseats.com/recipes/2011/10/applejack-rabbit-classic-apple-brandy-cocktail-pdt-recipe.html", "description": "At PDT, Jim Meehan uses local Deep Mountain Grade B maple syrup in this classic cocktail, but any Grade B syrup will work. It adds a deep, complex flavor to this bright, tart, and delicious drink.", "totalTime": "2 minutes", "recipeYield": "makes 1 cocktail", "recipeCategory": ["Brandy and Cognac", "Halloween"], "recipeIngredient": ["2 ounces Laird's Bonded Apple Brandy", "3/4 ounce fresh lemon juice", "3/4 ounce fresh orange juice", "1/2 ounce Deep Mountain Grade B Maple Syrup"], "recipeInstructions": [{"@context": "http://schema.org", "@type": "HowToStep", "text": "<p>Add apple brandy, lemon juice, orange juice, and maple syrup to a cocktail shaker and fill with ice. Shake until well chilled, about 15 seconds, and strain into a chilled coupe.</p>"}]}