{"@context": "http://schema.org", "@type": "Recipe", "nutrition": {}, "image": "https://www.seriouseats.com/recipes/images/2014/02/20140202-dandelion.jpg", "author": {"@type": "Person", "name": "Nick Caruana"}, "recipeCuisine": "", "keywords": ["chartreuse", "cocktail", "malort", "vermouth"], "aggregateRating": {"@type": "AggregateRating", "ratingValue": "", "ratingCount": ""}, "name": "Dandelion", "link": "https://www.seriouseats.com/recipes/2014/02/dandelion-cocktail-recipe-chartreuse-vermouth-malort-drink-recipe.html", "description": "This variation on the classic Chrysanthemum cocktail uses a Yellow and Green Chartreuse combination in place of Benedictine, and subs in bitter Mal\u00f6rt in place of the more traditional absinthe.", "totalTime": "2 minutes", "recipeYield": "makes 1 cocktail", "recipeCategory": ["Liqueur and Fortified Wines"], "recipeIngredient": ["2 ounces Vya Extra Dry vermouth", "3/4 ounce Yellow Chartreuse", "1/4 ounce Green Chartreuse", "1/3 ounce Mal\u00f6rt", "Garnish: orange twist"], "recipeInstructions": [{"@context": "http://schema.org", "@type": "HowToStep", "text": "<p>Fill a mixing glass 2/3 full with ice. Add vermouth, Yellow Chartreuse, Green Chartreuse and Malort. Stir until well chilled, about 20 seconds.</p>"}, {"@context": "http://schema.org", "@type": "HowToStep", "text": "<p>Strain into a chilled cocktail glass. Garnish with the orange twist and serve.</p>"}]}