{"@context": "http://schema.org", "@type": "Recipe", "nutrition": {}, "image": "https://www.seriouseats.com/recipes/images/2015/06/20150604-barbecue-sauce-daniel-gritzer-31.jpg", "author": {"@type": "Person", "name": "Daniel Gritzer"}, "recipeCuisine": "", "keywords": ["barbecue", "coffee", "grill", "sauce"], "aggregateRating": {"@type": "AggregateRating", "ratingValue": "", "ratingCount": ""}, "name": "Coffee-Ginger Barbecue Sauce", "link": "https://www.seriouseats.com/recipes/2015/06/coffee-ginger-barbecue-sauce-recipe.html", "description": "For this easy barbecue sauce, a ketchup base is spiked with a half cup of strong coffee, freshly grated ginger, a little dark chocolate, and molasses. Just a hint of smoked paprika builds an extra layer of aromatic mystery.", "totalTime": "20 minutes", "recipeYield": "Makes about 2 cups", "recipeCategory": ["Condiments and Sauces"], "recipeIngredient": ["1 cup ketchup", "1/2 cup strong coffee or espresso (see note)", "1 tablespoon Worcestershire sauce", "1 tablespoon molasses", "1 (2-inch) knob peeled fresh ginger, grated on a microplane", "1/2 ounce dark (70%) chocolate", "1/4 teaspoon smoked paprika", "Kosher salt and freshly ground black pepper"], "recipeInstructions": [{"@context": "http://schema.org", "@type": "HowToStep", "text": "<p>In a medium saucepan, combine ketchup, coffee, Worcestershire sauce, molasses, and ginger and bring to a low simmer, stirring occasionally, over medium heat. Stir in chocolate and smoked paprika until chocolate is melted, then let simmer over very low heat, stirring occasionally, until flavors have mellowed and melded, 5-10 minutes. Season with salt and pepper.</p>"}]}