{"@context": "http://schema.org", "@type": "Recipe", "nutrition": {}, "image": "https://www.seriouseats.com/2019/03/20190314-three-piece-suit-sherry-tequila-cocktail-vicky-wasik-2.jpg", "author": {"@type": "Person", "name": "Maggie Hoffman"}, "recipeCuisine": "", "keywords": ["big batch", "cocktail", "drink", "entertaining", "party", "sherry", "tequila"], "aggregateRating": {"@type": "AggregateRating", "ratingValue": "", "ratingCount": ""}, "name": "Three-Piece Suit (Tequila and Sherry Big-Batch Cocktail)", "link": "https://www.seriouseats.com/recipes/2019/04/three-piece-suit-tequila-and-sherry-big-batch-cocktail.html", "description": "Designed to be made in advance while being perfectly balanced, this tequila and sherry cocktail is a killer party drink. When your guests arrive, just open the bottle and start pouring.", "totalTime": "5 minutes", "recipeYield": "Serves about 8 in a 1-liter swing-top bottle", "recipeCategory": ["Liqueur and Fortified Wines", "Tequila"], "recipeIngredient": ["2 cups (475ml) reposado tequila", "1 cup (235ml) oloroso sherry", "2 teaspoons (10ml) orange bitters", "1/4 cup 1:1 simple syrup (see note)", "3/4 cup (175ml) water"], "recipeInstructions": [{"@context": "http://schema.org", "@type": "HowToStep", "text": "At least 2 hours and up to 4 hours before serving, use a small funnel to pour tequila, oloroso sherry, bitters, simple syrup, and water into a 1-liter swing-top bottle. Seal, turn gently end over end to mix, and chill in freezer. (If you\u2019d prefer to batch further in advance, refrigerate filled bottle, then place in freezer an hour or two before serving.)"}]}