{"@context": "http://schema.org", "@type": "Recipe", "name": "Scallop Salsa Cruda", "description": "Fresh scallops are served with a fresh tomato salad in this no-effort summer dish. Because they\u2019re being served raw, it\u2019s important to purchase high-quality scallops. Many store-bought options are soaked in a phosphate solution that plumps them up with water (therefore bumping up the price), so it\u2019s worth seeking out scallops that are labeled \u201cdry\u201d or \u201cdry-packed\" for more pure flavor.", "author": {"@type": "Person", "name": "Mark Bittman"}, "image": "https://static01.nyt.com/images/2014/05/09/dining/Scallop-Salsa-Cruda/Scallop-Salsa-Cruda-articleLarge.jpg", "totalTime": "PT5M", "recipeYield": "", "recipeCuisine": "", "recipeCategory": "easy, quick", "keywords": "appetizer, parsley, scallops, tomato, summer", "aggregateRating": null, "nutrition": {"@context": "http://schema.org", "@type": "NutritionInformation", "calories": 130, "unsaturatedFatContent": "6 grams", "carbohydrateContent": "6 grams", "cholesterolContent": null, "fatContent": "7 grams", "fiberContent": "1 gram", "proteinContent": "10 grams", "saturatedFatContent": "1 gram", "sodiumContent": "321 milligrams", "sugarContent": "2 grams", "transFatContent": "0 grams"}, "recipeIngredient": ["8 large scallops", "1 1/2 cups chopped ripe tomatoes", "1/2 cup chopped fresh parsley", "2 tablespoons olive oil", "2 tablespoons balsamic vinegar", "1 teaspoon minced garlic", "Salt and pepper"], "recipeInstructions": [{"@context": "http://schema.org", "@type": "HowToStep", "text": "Quarter the scallops. In a medium bowl, gently toss the scallops with the tomatoes, parsley, oil, vinegar and garlic. Season to taste with salt and pepper and serve immediately."}]}