{"@context": "http://schema.org", "@type": "Recipe", "name": "Soft-Shell Crabs With Brown Butter", "description": "", "author": {"@type": "Person", "name": "Pierre Franey"}, "image": null, "totalTime": "PT10M", "recipeYield": "4 servings", "recipeCuisine": "", "recipeCategory": "dinner, easy, quick", "keywords": "butter, crab, seafood, main course", "aggregateRating": {"@type": "AggregateRating", "ratingValue": 5, "ratingCount": 8}, "nutrition": {"@context": "http://schema.org", "@type": "NutritionInformation", "calories": 238, "unsaturatedFatContent": "9 grams", "carbohydrateContent": "19 grams", "cholesterolContent": null, "fatContent": "17 grams", "fiberContent": "2 grams", "proteinContent": "6 grams", "saturatedFatContent": "6 grams", "sodiumContent": "300 milligrams", "sugarContent": "2 grams", "transFatContent": "0 grams"}, "recipeIngredient": ["4 large or 8 small soft-shell crabs, dressed for cooking", "1/4 cup milk", "1/8 teaspoon cayenne pepper", "Salt and freshly ground pepper to taste", "1/2 cup flour", "2 tablespoons vegetable oil", "4 slices peeled lemon", "3 tablespoons butter", "1 tablespoon lemon juice", "3 tablespoons finely chopped parsley"], "recipeInstructions": [{"@context": "http://schema.org", "@type": "HowToStep", "text": "Put the crabs in a shallow dish in one layer and add the milk, cayenne, salt and pepper. Turn the crabs in the milk."}, {"@context": "http://schema.org", "@type": "HowToStep", "text": "Dip the crabs immediately into the flour, turning to coat them well. Shake off the excess flour."}, {"@context": "http://schema.org", "@type": "HowToStep", "text": "Heat the oil until quite hot in a nonstick skillet large enough to hold the crabs in one layer. Add the crabs, belly side down. Cook for 4 to 5 minutes (more or less, depending on the size of the crabs) until golden brown on both sides and cooked through."}, {"@context": "http://schema.org", "@type": "HowToStep", "text": "Transfer the crabs to a warm serving platter. Garnish with lemon slices."}, {"@context": "http://schema.org", "@type": "HowToStep", "text": "Wipe out the skillet with a clean cloth and add the butter. When it is bubbling and turned hazelnut color add the lemon juice and pour the mixture over the crabs. Sprinkle with parsley and serve immediately."}]}