{"@context": "http://schema.org", "@type": "Recipe", "name": "Minted Yogurt Sauce", "description": "", "author": {"@type": "Person", "name": "Sam Sifton"}, "image": "https://static01.nyt.com/images/2014/04/07/dining/minted/minted-articleLarge.jpg", "totalTime": "PT5M", "recipeYield": "", "recipeCuisine": "mediterranean", "recipeCategory": "easy, quick, condiments", "keywords": "gluten-free, vegetarian, side dish", "aggregateRating": {"@type": "AggregateRating", "ratingValue": 4, "ratingCount": 26}, "recipeIngredient": ["1 cup best-quality whole milk yogurt", "1/2 cup cr\u00e8me fra\u00eeche", "1/4 cup mint, minced", "1 tablespoon chives, minced", "1/2 clove garlic, finely diced or grated on Microplane", "Zest of 1 lemon", "Tabasco or other hot pepper sauce, to taste", "Kosher salt", "freshly ground black pepper, to taste"], "recipeInstructions": [{"@context": "http://schema.org", "@type": "HowToStep", "text": "Combine yogurt, cr\u00e8me fra\u00eeche, mint, chives, garlic and lemon zest in a medium-size nonreactive bowl, then whisk to a smooth consistency."}, {"@context": "http://schema.org", "@type": "HowToStep", "text": "Season to taste, transfer to small bowls and serve with lamb ribs.\u00a0"}], "link": "https://cooking.nytimes.com/recipes/1013642-minted-yogurt-sauce"}