{"@context": "http://schema.org", "@type": "Recipe", "name": "The Improved Dirty Martini", "description": "\u201cDirty martini\u201d is a dirty word for many bartenders who find the drink \u2014 a martini with a salty slop of olive brine \u2014 unimaginative and unappetizing. Naren Young, a New York bartender, decided to create a better version, called Olives 7 Ways, with several bespoke ingredients. That cocktail, served at Saxon & Parole, is fairly complicated to make, so Mr. Young came up with yet another, easier variation for the home bartender.", "author": {"@type": "Person", "name": "Robert Simonson"}, "image": "https://static01.nyt.com/images/2014/02/12/dining/12DIRTY1_SPAN/12DIRTY1-articleLarge.jpg", "recipeYield": "1 drink", "recipeCuisine": "", "recipeCategory": "cocktails", "keywords": "gin, olives", "aggregateRating": {"@type": "AggregateRating", "ratingValue": 4, "ratingCount": 45}, "nutrition": {"@context": "http://schema.org", "@type": "NutritionInformation", "calories": 491, "unsaturatedFatContent": "5 grams", "carbohydrateContent": "14 grams", "cholesterolContent": null, "fatContent": "6 grams", "fiberContent": "2 grams", "proteinContent": "1 gram", "saturatedFatContent": "1 gram", "sodiumContent": "461 milligrams", "sugarContent": "3 grams", "transFatContent": null}, "recipeIngredient": ["375 milliliters dry vermouth, preferably Noilly Prat", "1/2 cup chopped Cerignola olives", "1 1/2 ounces navy-strength gin, preferably Perry\u2019s Tot", "A few drops of extra-virgin olive oil", "Mixed olives, for serving"], "recipeInstructions": [{"@context": "http://schema.org", "@type": "HowToStep", "text": "Combine vermouth and chopped olives in a sealed glass container and let sit for 3 days. Shake periodically."}, {"@context": "http://schema.org", "@type": "HowToStep", "text": "Chill a cocktail glass by filling it with ice or putting it in the freezer for about 5 minutes."}, {"@context": "http://schema.org", "@type": "HowToStep", "text": "In a mixing glass filled three-quarters full with ice, pour the gin and 1 1/2 ounces of the infused vermouth. Stir until chilled, about 30 seconds, and strain into the chilled glass. Carefully drip a few drops of olive oil (with an eye-dropper, if possible) onto the drink\u2019s surface. Serve with a small dish of mixed olives."}]}