{"@context": "http://schema.org", "@type": "Recipe", "name": "Strawberry Sauce", "description": "", "author": {"@type": "Person", "name": "Bryan Miller"}, "image": null, "totalTime": "PT10M", "recipeYield": "Enough for 8 souffles", "recipeCuisine": "", "recipeCategory": "dinner", "keywords": "dessert, fruit liqueur, strawberry, sugar", "aggregateRating": null, "nutrition": {"@context": "http://schema.org", "@type": "NutritionInformation", "calories": 54, "unsaturatedFatContent": "0 grams", "carbohydrateContent": "12 grams", "cholesterolContent": null, "fatContent": "0 grams", "fiberContent": "0 grams", "proteinContent": "0 grams", "saturatedFatContent": "0 grams", "sodiumContent": "1 milligram", "sugarContent": "11 grams", "transFatContent": null}, "recipeIngredient": ["1/2 pint fresh strawberries, cleaned and sliced thinly", "1/3 cup sugar", "2 tablespoons kirsch or other fruit liqueur"], "recipeInstructions": [{"@context": "http://schema.org", "@type": "HowToStep", "text": "Place strawberries and sugar in saucepan over medium heat. Cook, stirring occasionally, for 5 minutes. Add liqueur and keep warm until serving."}]}