{"@context": "http://schema.org", "@type": "Recipe", "name": "Mixed Green Salad With Roquefort Dressing", "description": "", "author": {"@type": "Person", "name": "Pierre Franey"}, "image": null, "totalTime": "PT5M", "recipeYield": "4 servings", "recipeCuisine": "", "recipeCategory": "easy, quick, salads and dressings", "keywords": "dijon mustard, roquefort cheese, salad", "aggregateRating": {"@type": "AggregateRating", "ratingValue": 4, "ratingCount": 41}, "recipeIngredient": ["2 tablespoons red-wine vinegar", "1 tablespoon Dijon mustard", "1/2 cup crumbled Roquefort", "4 tablespoons olive or corn oil", "Salt and freshly ground pepper to taste", "8 cups loosely packed bite-size pieces of watercress, red-leaf or Boston lettuce, radicchio or Belgian endive"], "recipeInstructions": [{"@context": "http://schema.org", "@type": "HowToStep", "text": "Combine the vinegar, mustard and cheese in a bowl. Blend well with a wire whisk, and stir in the oil and salt and pepper to taste. Place the salad greens into a bowl, toss well with the dressing."}], "link": "https://cooking.nytimes.com/recipes/10372-mixed-green-salad-with-roquefort-dressing"}