{"@context": "http://schema.org", "@type": "Recipe", "name": "Chirashi (Scattered) Sushi", "description": "", "author": {"@type": "Person", "name": "Matt Lee And Ted Lee"}, "image": null, "totalTime": "PT30M", "recipeYield": "6 servings", "recipeCuisine": "japanese", "recipeCategory": "dinner, lunch, weekday", "keywords": "appetizer, main course, dairy-free, gluten-free, nut-free, vegetarian, fish, nori, sushi rice", "aggregateRating": {"@type": "AggregateRating", "ratingValue": 4, "ratingCount": 11}, "nutrition": {"@context": "http://schema.org", "@type": "NutritionInformation", "calories": 483, "unsaturatedFatContent": "11 grams", "carbohydrateContent": "55 grams", "cholesterolContent": null, "fatContent": "14 grams", "fiberContent": "6 grams", "proteinContent": "33 grams", "saturatedFatContent": "2 grams", "sodiumContent": "1099 milligrams", "sugarContent": "2 grams", "transFatContent": null}, "recipeIngredient": ["6 cups prepared sushi rice (<a href=\"http://cooking.nytimes.com/recipes/10754-sushi-rice\">see recipe</a>)", "2 Hass avocados in 1/2-inch strips", "Salt", "1 pound cucumber, carrot or daikon, or a combination, cut into matchsticks", "2 sheets nori (7 by 8 inches), cut into confetti", "2 pounds fillets of fresh salmon, tuna, yellowtail, fluke or striped bass, in slices 3 inches by 1 inch by 1/4 inch thick", "1 bunch scallions, cut in thin rings halfway up the green tops", "2 teaspoons sesame seeds"], "recipeInstructions": [{"@context": "http://schema.org", "@type": "HowToStep", "text": "Place a cup of rice, cooled to just above room temperature, in the bottom of each of 6 bowls, and add a layer of the avocado slices, distributing evenly in any pattern you choose. Sprinkle a pinch or two of salt over each bowl. Add the raw matchstick vegetables in an even, randomly arranged layer, and sprinkle on the nori confetti. Add the fish on top, arranging as you wish, perhaps in twists or rolls. Scatter scallions and sesame seeds on top. Serve with condiments like soy sauce, wasabi, pickled ginger and rice vinegar, so diners can season and toss sushi with chopsticks or spoons."}], "link": "https://cooking.nytimes.com/recipes/10753-chirashi-scattered-sushi"}