{"@context": "http://schema.org", "@type": "Recipe", "name": "New-Wave Piccalilli", "description": "This New England staple, originally brought over from India, is best used as a topping after grilling meat or fish. It also adds zip to sandwiches.", "author": {"@type": "Person", "name": "Molly O'Neill"}, "image": null, "totalTime": "PT10M", "recipeYield": "Two cups", "recipeCuisine": "british", "recipeCategory": "condiments, dips and spreads", "keywords": "balsamic vinegar, bell pepper, poblano pepper", "aggregateRating": null, "nutrition": {"@context": "http://schema.org", "@type": "NutritionInformation", "calories": 110, "unsaturatedFatContent": "0 grams", "carbohydrateContent": "25 grams", "cholesterolContent": null, "fatContent": "1 gram", "fiberContent": "2 grams", "proteinContent": "2 grams", "saturatedFatContent": "0 grams", "sodiumContent": "504 milligrams", "sugarContent": "14 grams", "transFatContent": null}, "recipeIngredient": ["3 red and 3 yellow bell peppers, roasted, skinned, stemmed, cored and cut into 1/2-inch dice", "", "2 poblano peppers, roasted, skinned, stemmed, cored and cut into 1/2-inch dice", "1/2 cup diced red onion", "2 jalapenos, stemmed, seeded and minced", "1 clove garlic, peeled and minced", "1/4 cup light brown sugar", "1/4 cup plus 1 teaspoon balsamic vinegar", "1 teaspoon salt", "1 teaspoon mustard seeds"], "recipeInstructions": [{"@context": "http://schema.org", "@type": "HowToStep", "text": "In a medium bowl, combine the roasted peppers, red onion, jalapenos and garlic. Combine the brown sugar and vinegar in a small saucepan over low heat. Cook until sugar is melted. Pour over the pepper mixture and toss with the salt and mustard seeds. Store in an airtight container."}], "link": "https://cooking.nytimes.com/recipes/10885-new-wave-piccalilli"}