{"@context": "http://schema.org", "@type": "Recipe", "name": "Old-World Raspberry-Cheese Squares", "description": "", "author": {"@type": "Person", "name": "Marialisa Calta"}, "image": null, "totalTime": "PT45M", "recipeYield": "32 cookies", "recipeCuisine": "", "recipeCategory": "", "keywords": "cheddar, raspberry jam, winter", "aggregateRating": null, "nutrition": {"@context": "http://schema.org", "@type": "NutritionInformation", "calories": 97, "unsaturatedFatContent": "1 gram", "carbohydrateContent": "13 grams", "cholesterolContent": null, "fatContent": "4 grams", "fiberContent": "0 grams", "proteinContent": "2 grams", "saturatedFatContent": "3 grams", "sodiumContent": "47 milligrams", "sugarContent": "6 grams", "transFatContent": "0 grams"}, "recipeIngredient": ["1 1/2 cups flour", "1 teaspoon baking powder", "Pinch of salt", "3 tablespoons packed brown sugar", "1/2 cup butter or margarine", "1 cup shredded Cheddar cheese", "1 cup raspberry jam", "1/2 cup finely chopped walnuts"], "recipeInstructions": [{"@context": "http://schema.org", "@type": "HowToStep", "text": "Preheat the oven to 350 degrees."}, {"@context": "http://schema.org", "@type": "HowToStep", "text": "In a medium-size bowl, combine the flour, baking powder, salt and brown sugar."}, {"@context": "http://schema.org", "@type": "HowToStep", "text": "Using two knives or a pastry blender, cut in the butter or margarine until the mixture resembles crumbs. Stir in the cheese. Remove 3/4 cup of the mixture and set aside."}, {"@context": "http://schema.org", "@type": "HowToStep", "text": "Press the remaining mixture evenly into the bottom of an 8-inch-square baking pan. Spread the jam evenly over the crust. Sprinkle with the nuts and then the reserved crumb mixture. Press gently."}, {"@context": "http://schema.org", "@type": "HowToStep", "text": "Bake 25 to 30 minutes or until golden."}, {"@context": "http://schema.org", "@type": "HowToStep", "text": "Cool completely in the pan. Cut the cooled pastry into 2-by-1-inch bars. Store, well-wrapped, in the refrigerator."}], "link": "https://cooking.nytimes.com/recipes/1145-old-world-raspberry-cheese-squares"}