{"@context": "http://schema.org", "@type": "Recipe", "name": "Baked Apples With Blackberry Jam", "description": "", "author": {"@type": "Person", "name": "Melissa Clark"}, "image": null, "totalTime": "PT1H15M", "recipeYield": "4 servings", "recipeCuisine": "", "recipeCategory": "", "keywords": "apple, blackberry jam, dessert, fall", "aggregateRating": {"@type": "AggregateRating", "ratingValue": 4, "ratingCount": 10}, "nutrition": {"@context": "http://schema.org", "@type": "NutritionInformation", "calories": 204, "unsaturatedFatContent": "2 grams", "carbohydrateContent": "37 grams", "cholesterolContent": null, "fatContent": "6 grams", "fiberContent": "4 grams", "proteinContent": "1 gram", "saturatedFatContent": "4 grams", "sodiumContent": "11 milligrams", "sugarContent": "27 grams", "transFatContent": "0 grams"}, "recipeIngredient": ["4 Golden Delicious apples, peeled and cored", "2 tablespoons unsalted butter", "4 tablespoons blackberry jam", "Cr\u00e8me fra\u00eeche or sour cream, for serving (optional)"], "recipeInstructions": [{"@context": "http://schema.org", "@type": "HowToStep", "text": "Preheat oven to 375 degrees. Place apples in baking dish."}, {"@context": "http://schema.org", "@type": "HowToStep", "text": "Stuff each apple with 1/2 tablespoon butter and then 1 tablespoon jam."}, {"@context": "http://schema.org", "@type": "HowToStep", "text": "Bake, basting occasionally, until apples are very tender and glazed, about 1 hour. Serve warm or at room temperature, with cr&#232;me fra&#238;che or sour cream, if desired."}], "link": "https://cooking.nytimes.com/recipes/11949-baked-apples-with-blackberry-jam"}