{"@context": "http://schema.org", "@type": "Recipe", "name": "Skewered Crisp Shiitakes With Garlic", "description": "", "author": {"@type": "Person", "name": "Mark Bittman"}, "image": null, "totalTime": "PT1H", "recipeYield": "40 skewers", "recipeCuisine": "", "recipeCategory": "", "keywords": "appetizer, garlic, shiitake, vegan, vegetarian", "aggregateRating": null, "nutrition": {"@context": "http://schema.org", "@type": "NutritionInformation", "calories": 20, "unsaturatedFatContent": "2 grams", "carbohydrateContent": "1 gram", "cholesterolContent": null, "fatContent": "2 grams", "fiberContent": "0 grams", "proteinContent": "0 grams", "saturatedFatContent": "0 grams", "sodiumContent": "31 milligrams", "sugarContent": "0 grams", "transFatContent": null}, "recipeIngredient": ["40 shiitake caps, about 1 pound (reserve stems for stock or discard)", "1/3 cup extra virgin olive oil", "1 tablespoon chopped garlic", "Salt and pepper"], "recipeInstructions": [{"@context": "http://schema.org", "@type": "HowToStep", "text": "Preheat oven to 450 degrees. Put shiitakes in roasting pan in one layer and add olive oil. Roast for about 20 minutes, until shiitakes have begun to shrink. Stir in garlic, salt and pepper, and return to oven, tossing and turning occasionally, until edges of shiitakes are crisp, another 20 minutes or so."}, {"@context": "http://schema.org", "@type": "HowToStep", "text": "Cool slightly, then skewer mushrooms on toothpicks. Serve warm."}], "link": "https://cooking.nytimes.com/recipes/1864-skewered-crisp-shiitakes-with-garlic"}