{"@context": "http://schema.org", "@type": "Recipe", "name": "Two-Way Beans", "description": "", "author": {"@type": "Person", "name": "Marian Burros"}, "image": null, "totalTime": "PT4H", "recipeYield": "About 5 cups", "recipeCuisine": "", "recipeCategory": "dinner", "keywords": "beans, carrot, smoked turkey, high fiber, main course, winter", "aggregateRating": null, "nutrition": {"@context": "http://schema.org", "@type": "NutritionInformation", "calories": 294, "unsaturatedFatContent": "7 grams", "carbohydrateContent": "19 grams", "cholesterolContent": null, "fatContent": "11 grams", "fiberContent": "5 grams", "proteinContent": "29 grams", "saturatedFatContent": "4 grams", "sodiumContent": "108 milligrams", "sugarContent": "2 grams", "transFatContent": "0 grams"}, "recipeIngredient": ["2 cups dried beans, in any combination", "2 quarts water", "4 teaspoons dried oregano, thyme or marjoram", "1 bay leaf", "4 cloves garlic", "1 pound smoked turkey or chicken, skin removed, or smoked pork, fat removed, and meat cut in large chunks", "4 carrots, peeled and halved", "2 large onions, quartered"], "recipeInstructions": [{"@context": "http://schema.org", "@type": "HowToStep", "text": "Combine beans with water and 2 teaspoons of the dried herb and bay leaf. Bring to boil and boil 2 minutes. Remove from heat and allow to sit for 1 hour. Drain."}, {"@context": "http://schema.org", "@type": "HowToStep", "text": "Add 2 quarts fresh water to drained beans with remaining dried herbs, garlic, smoked meat, carrots and onion. Bring to a boil; reduce heat, cover and simmer 2 1/2 to 3 hours, until beans are soft but still hold their shape. Drain and discard the meat and bay leaf."}], "link": "https://cooking.nytimes.com/recipes/3013-two-way-beans"}