{"@context": "http://schema.org", "@type": "Recipe", "name": "Craig Claiborne's Croutons", "description": "", "author": {"@type": "Person", "name": "Craig Claiborne"}, "image": null, "totalTime": "PT10M", "recipeYield": "24 or more", "recipeCuisine": "french", "recipeCategory": "condiments, salads and dressings", "keywords": "bread", "aggregateRating": null, "nutrition": {"@context": "http://schema.org", "@type": "NutritionInformation", "calories": 44, "unsaturatedFatContent": "1 gram", "carbohydrateContent": "7 grams", "cholesterolContent": null, "fatContent": "1 gram", "fiberContent": "0 grams", "proteinContent": "1 gram", "saturatedFatContent": "0 grams", "sodiumContent": "75 milligrams", "sugarContent": "1 gram", "transFatContent": "0 grams"}, "recipeIngredient": ["1 thin, long loaf (baguette) crusty French bread", "1 clove garlic, peeled and cut in half crosswise", "2 tablespoons olive oil"], "recipeInstructions": [{"@context": "http://schema.org", "@type": "HowToStep", "text": "Preheat the broiler."}, {"@context": "http://schema.org", "@type": "HowToStep", "text": "Rub the crust of the uncut loaf all over with the cut pieces of garlic."}, {"@context": "http://schema.org", "@type": "HowToStep", "text": "Cut the bread into thin crosswise slices. Arrange the slices in one layer on a baking sheet. Brush the slices on one side with oil. Turn and brush them on the second side. Place the slices under the broiler and cook briefly until golden brown on top."}], "link": "https://cooking.nytimes.com/recipes/3109-craig-claibornes-croutons"}