{"@context": "http://schema.org", "@type": "Recipe", "name": "Chicken Tarragon With Cr\u00e8me Fra\u00eeche", "description": "", "author": {"@type": "Person", "name": "Moira Hodgson"}, "image": null, "totalTime": "PT20M", "recipeYield": "4 servings", "recipeCuisine": "", "recipeCategory": "dinner, easy, quick, weekday", "keywords": "butter, chicken breast, cr\u00e8me fra\u00eeche, poultry, tarragon, main course", "aggregateRating": {"@type": "AggregateRating", "ratingValue": 5, "ratingCount": 20}, "nutrition": {"@context": "http://schema.org", "@type": "NutritionInformation", "calories": 442, "unsaturatedFatContent": "14 grams", "carbohydrateContent": "5 grams", "cholesterolContent": null, "fatContent": "29 grams", "fiberContent": "1 gram", "proteinContent": "39 grams", "saturatedFatContent": "12 grams", "sodiumContent": "522 milligrams", "sugarContent": "1 gram", "transFatContent": "0 grams"}, "recipeIngredient": ["4 chicken breasts, boned", "2 tablespoons butter", "Coarse salt and freshly ground pepper to taste", "1 small bunch tarragon", "1/2 to 3/4 cup cr\u00e8me fra\u00eeche"], "recipeInstructions": [{"@context": "http://schema.org", "@type": "HowToStep", "text": "Preheat oven to 375 degrees. In a fireproof pan, heat the butter, and brown the chicken lightly. Season with salt and pepper, add half the tarragon. Cover with foil and bake for 10 to 15 minutes or until chicken breasts are cooked."}, {"@context": "http://schema.org", "@type": "HowToStep", "text": "Remove from oven. Stir in the cr\u00e8me fra\u00eeche, heat through and sprinkle with remaining tarragon leaves."}], "link": "https://cooking.nytimes.com/recipes/6327-chicken-tarragon-with-creme-fraiche"}