{"@context": "http://schema.org", "@type": "Recipe", "name": "White Gazpacho", "description": "", "author": {"@type": "Person", "name": "Suzanne Hamlin"}, "image": null, "totalTime": "PT30M", "recipeYield": "6 servings", "recipeCuisine": "spanish", "recipeCategory": "soups and stews", "keywords": "almonds, chicken stock, extra virgin olive oil, french bread, garlic, green grape, white wine vinegar, appetizer, raw, summer", "aggregateRating": null, "nutrition": {"@context": "http://schema.org", "@type": "NutritionInformation", "calories": 336, "unsaturatedFatContent": "20 grams", "carbohydrateContent": "22 grams", "cholesterolContent": null, "fatContent": "24 grams", "fiberContent": "3 grams", "proteinContent": "11 grams", "saturatedFatContent": "3 grams", "sodiumContent": "505 milligrams", "sugarContent": "8 grams", "transFatContent": "0 grams"}, "recipeIngredient": ["1 cup blanched almonds", "2 cloves garlic, peeled and halved", "3 slices French or Italian bread, crusts removed", "1/4 cup water", "4 cups cold chicken or vegetable stock, or water", "1/4 cup fruity olive oil", "3 tablespoons white wine vinegar", "1/2 teaspoon salt, or to taste", "1 cup seedless green grapes, halved", "1/2 cup lightly toasted croutons"], "recipeInstructions": [{"@context": "http://schema.org", "@type": "HowToStep", "text": "Preheat oven to 350 degrees. Spread almonds on a cookie sheet, and bake until lightly toasted, about 15 minutes. Cool."}, {"@context": "http://schema.org", "@type": "HowToStep", "text": "In a food processor or blender, blend almonds and garlic into a uniformly fine, gritty paste."}, {"@context": "http://schema.org", "@type": "HowToStep", "text": "In a small bowl, moisten the bread in 1/4 cup water and squeeze dry. Add to the almond-garlic mix, and blend. Add 4 cups stock or water, olive oil, vinegar and salt. Blend until smooth. If a fine texture is desired, strain through a medium-fine sieve. Cover and chill 4 hours or overnight."}, {"@context": "http://schema.org", "@type": "HowToStep", "text": "To serve, taste for salt and stir in grapes. Ladle into bowls and scatter croutons on top."}]}