{"@context": "http://schema.org", "@type": "Recipe", "name": "Seaweed Salad With Cucumber", "description": "", "author": {"@type": "Person", "name": "Mark Bittman"}, "image": null, "totalTime": "PT20M", "recipeYield": "4 servings", "recipeCuisine": "", "recipeCategory": "salads and dressings", "keywords": "chicken, cucumber, seaweed, gluten-free, raw", "aggregateRating": null, "nutrition": {"@context": "http://schema.org", "@type": "NutritionInformation", "calories": 55, "unsaturatedFatContent": "3 grams", "carbohydrateContent": "4 grams", "cholesterolContent": null, "fatContent": "4 grams", "fiberContent": "1 gram", "proteinContent": "2 grams", "saturatedFatContent": "1 gram", "sodiumContent": "445 milligrams", "sugarContent": "1 gram", "transFatContent": null}, "recipeIngredient": ["1 ounce wakame or assorted seaweeds", "1/2 pound thin-skinned cucumber", "4 ounces konyaku, shredded (optional)", "1/2 to 1 pound cooked chicken or cooked shrimp (optional)", "1/4 cup minced shallot, scallion or red onion", "2 tablespoons soy sauce", "1 tablespoon rice wine vinegar", "1 tablespoon mirin", "1 tablespoon sesame oil", "1/4 teaspoon cayenne, or to taste", "Salt, if necessary", "1 tablespoon toasted sesame seeds (optional)"], "recipeInstructions": [{"@context": "http://schema.org", "@type": "HowToStep", "text": "Rinse seaweed, and soak it in at least 10 times its volume of water."}, {"@context": "http://schema.org", "@type": "HowToStep", "text": "Wash and dice cucumber; do not peel unless necessary. When seaweed is tender, 5 minutes later, add konyaku if you are using it, then drain and squeeze mixture to remove excess water. Pick through seaweed to sort out hard bits; chop if pieces are large. Combine cucumber and seaweed; shred or chop chicken or shrimp if necessary, and add to bowl."}, {"@context": "http://schema.org", "@type": "HowToStep", "text": "Add all remaining ingredients except sesame seeds, and toss; taste, and add salt or other seasonings as necessary; serve garnished with the sesame seeds."}], "link": "https://cooking.nytimes.com/recipes/7694-seaweed-salad-with-cucumber"}