{"@context": "http://schema.org", "@type": "Recipe", "name": "Indian Rice With Shrimp", "description": "", "author": {"@type": "Person", "name": "Molly O'Neill"}, "image": null, "totalTime": "PT1H15M", "recipeYield": "Six to eight servings", "recipeCuisine": "indian", "recipeCategory": "", "keywords": "rice, shrimp, tomato, side dish", "aggregateRating": null, "nutrition": {"@context": "http://schema.org", "@type": "NutritionInformation", "calories": 243, "unsaturatedFatContent": "6 grams", "carbohydrateContent": "35 grams", "cholesterolContent": null, "fatContent": "7 grams", "fiberContent": "1 gram", "proteinContent": "9 grams", "saturatedFatContent": "1 gram", "sodiumContent": "486 milligrams", "sugarContent": "3 grams", "transFatContent": "0 grams"}, "recipeIngredient": ["1 1/2 cups unconverted rice (like Canilla )", "1 cup finely chopped fresh or well-drained canned tomatoes", "2 tablespoons finely chopped onion", "1 clove garlic, peeled", "3 tablespoons vegetable oil", "3 1/2 cups chicken broth, homemade or low-sodium canned", "1 teaspoon salt, plus more to taste", "1/3 cup thinly sliced carrot, optional", "1/2 cup peas or diced zucchini, optional", "1/2 teaspoon ground cumin", "1/4 teaspoon ground coriander", "1/4 teaspoon ground turmeric", "1/8 teaspoon crushed red pepper", "1/2 pound medium shrimp, shelled and deveined", "1/4 cup minced fresh coriander"], "recipeInstructions": [{"@context": "http://schema.org", "@type": "HowToStep", "text": "Follow the directions for <a href=\"http://cooking.nytimes.com/recipes/9937-mexican-rice?action=click&module=Global+Search+Recipe+Card&pgType=search&rank=3\">Mexican rice</a>, pureeing the cumin, ground coriander, turmeric and red pepper with the tomato mixture in Step 1."}, {"@context": "http://schema.org", "@type": "HowToStep", "text": "When liquid has been absorbed in Step 3, submerge the shrimp in the rice, before covering the pot with the towel. Cover and continue as in main recipe. Stir to distribute shrimp. Serve hot, garnishing each serving with fresh coriander."}], "link": "https://cooking.nytimes.com/recipes/9939-indian-rice-with-shrimp"}